Workbook

Sheet Bug Tracker - 85
A1: Bug ID | B1: Original Defect ID | C1: Test Case ID | D1: Level | E1: Module | F1: Submodule | G1: Scenario | H1: Test Type | I1: Role | J1: Priority | K1: Release Gate | L1: Original Status | M1: Bug Type | N1: Severity | O1: Bug Status | P1: Developer Name | Q1: Developer Rework Date | R1: Opened Date | S1: Target Fix Date | T1: QA Retest Date | U1: Retest Result | V1: Final Status | W1: Age Days | X1: Environment | Y1: Build | Z1: Fix Build | AA1: Tester | AB1: Preconditions | AC1: Test Data | AD1: Steps | AE1: Expected Result | AF1: Actual Result | AG1: Reason / Root Cause | AH1: Developer Rework Required | AI1: Fix Notes | AJ1: Evidence Link | AK1: Comments
A2: BUG-001 | B2: DL1001 | C2: L1-001 | D2: Level 1 | E2: Platform | G2: Provision a lab tenant | H2: Smoke | I2: Developer Admin | J2: High | K2: Yes | L2: Failed | M2: Functional Bug | N2: High | O2: Open | P2: Unassigned | R2: 46262 | U2: Pending | V2: Open | W2: =IF(R2="","",TODAY()-R2) -> 21 | X2: UAT | AA2: Premothan V | AB2: Required master data and user exist. | AC2: Use dedicated non-production test data. | AD2: 1. Sign in as Developer Admin. 2. Create a lab with an active plan and required modules. 3. Save or submit. 4. Refresh or reopen the record. 5. Compare the result with the pass condition. | AE2: The tenant is created, isolated and can open its login page. | AF2: Lab created successfully. But facing two bugs, and the concept needs to be altered. | AG2: Failed result requires rework: Lab created successfully. But facing two bugs, and the concept needs to be altered. | AH2: Fix Platform workflow for "Provision a lab tenant" so actual behavior matches expected result: The tenant is created, isolated and can open its login page. | AK2: Please refer to the evidence link
A3: BUG-002 | B3: DL1004 | C3: L1-004 | D3: Level 1 | E3: Inventory | G3: Load opening stock | H3: Smoke | I3: Inventory Manager | J3: High | K3: Yes | L3: Failed | M3: Functional Bug | N3: Low | O3: Open | P3: Unassigned | R3: 46268 | U3: Pending | V3: Open | W3: =IF(R3="","",TODAY()-R3) -> 15 | X3: UAT | AA3: Premothan V | AB3: Required master data and user exist. | AC3: Use dedicated non-production test data. | AD3: 1. Sign in as Inventory Manager. 2. Create required inventory masters and load stock with batch and expiry. 3. Save or submit. 4. Refresh or reopen the record. 5. Compare the result with the pass condition. | AE3: On-hand stock, batch, UOM and expiry are correct. | AF3: Created everything. But the name field length must be extended | AG3: Validation/UI rule issue: field constraints or required-field behavior do not match expected workflow. | AH3: Fix Inventory workflow for "Load opening stock" so actual behavior matches expected result: On-hand stock, batch, UOM and expiry are correct. | AK3: Need to retest
A4: BUG-003 | B4: DL1010 | C4: L1-010 | D4: Level 1 | E4: Samples | G4: Print or open sample barcode | H4: Smoke | I4: Phlebotomist | J4: High | K4: Yes | L4: Failed | M4: Functional Bug | N4: Medium | O4: Open | P4: Unassigned | U4: Not Required | V4: Open | W4: =IF(R4="","",TODAY()-R4) | X4: QA | AA4: Stephen | AB4: Required master data and user exist. | AC4: Use dedicated non-production test data. | AD4: 1. Sign in as Phlebotomist. 2. Open the generated sample and barcode. 3. Save or submit. 4. Refresh or reopen the record. 5. Compare the result with the pass condition. | AE4: Sample ID, barcode, patient, bill and required sample type match. | AF4: Can't create an appropriate role. | AG4: Access/RBAC setup issue: required role or permission does not allow the testcase workflow to complete. | AH4: Fix Samples workflow for "Print or open sample barcode" so actual behavior matches expected result: Sample ID, barcode, patient, bill and required sample type match.
A5: BUG-004 | B5: DL1011 | C5: L1-011 | D5: Level 1 | E5: Samples | G5: Collect the sample | H5: Smoke | I5: Phlebotomist | J5: High | K5: Yes | L5: Failed | M5: Functional Bug | N5: Medium | O5: Open | P5: Unassigned | U5: Not Required | V5: Open | W5: =IF(R5="","",TODAY()-R5) | X5: QA | AA5: Stephen | AB5: Required master data and user exist. | AC5: Use dedicated non-production test data. | AD5: 1. Sign in as Phlebotomist. 2. Verify two patient identifiers, record collection/received details and mark Collected. 3. Save or submit. 4. Refresh or reopen the record. 5. Compare the result with the pass condition. | AE5: Collection time, collector and custody event are saved. | AF5: Can't create an appropriate role. | AG5: Access/RBAC setup issue: required role or permission does not allow the testcase workflow to complete. | AH5: Fix Samples workflow for "Collect the sample" so actual behavior matches expected result: Collection time, collector and custody event are saved.
A6: BUG-005 | B6: DL1012 | C6: L1-012 | D6: Level 1 | E6: Samples | G6: Move sample to processing | H6: Smoke | I6: Lab Technician | J6: High | K6: Yes | L6: Failed | M6: Functional Bug | N6: High | O6: Open | P6: Unassigned | R6: 46267 | U6: Not Required | V6: Open | W6: =IF(R6="","",TODAY()-R6) -> 16 | X6: QA | AA6: Rishidharshini | AB6: Required master data and user exist. | AC6: Use dedicated non-production test data. | AD6: 1. Sign in as Lab Technician. 2. Open the collected sample and start processing. 3. Save or submit. 4. Refresh or reopen the record. 5. Compare the result with the pass condition. | AE6: Sample and bill-item statuses move forward in the correct order. | AF6: The sample is not coming to processing | AG6: Failed result requires rework: The sample is not coming to processing | AH6: Fix Samples workflow for "Move sample to processing" so actual behavior matches expected result: Sample and bill-item statuses move forward in the correct order. | AJ6: Defect SS
A7: BUG-006 | B7: DL1013 | C7: L1-013 | D7: Level 1 | E7: Inventory | G7: Reserve or monitor test inventory | H7: Smoke | I7: Lab Technician | J7: High | K7: Yes | L7: Failed | M7: Functional Bug | N7: High | O7: Open | P7: Unassigned | R7: 46267 | U7: Not Required | V7: Open | W7: =IF(R7="","",TODAY()-R7) -> 16 | X7: QA | AA7: Rishidharshini | AC7: Use dedicated non-production test data. | AD7: 1. Sign in as Lab Technician. 2. Check required item availability during sample processing. 3. Save or submit. 4. Refresh or reopen the record. 5. Compare the result with the pass condition. | AE7: Reserved/on-hand stock and warnings follow the implemented rule. | AF7: The Inventory Item can be submitted even if there is no stock and also when it begin to process, added inventory item is not available | AG7: Inventory workflow issue: stock, UOM, expiry, or master data behavior does not meet expected result. | AH7: Fix Inventory workflow for "Reserve or monitor test inventory" so actual behavior matches expected result: Reserved/on-hand stock and warnings follow the implemented rule. | AJ7: Defect SS
A8: BUG-007 | B8: DL1018 | C8: L1-018 | D8: Level 1 | E8: Notifications | G8: Check report release notification | H8: Smoke | I8: Lab Manager | J8: High | K8: Yes | L8: Failed | M8: Functional Bug | N8: High | O8: Open | P8: Unassigned | R8: 46268 | U8: Not Required | V8: Open | W8: =IF(R8="","",TODAY()-R8) -> 15 | X8: QA | AA8: Rishidharshini | AB8: Required master data and user exist. | AC8: Use dedicated non-production test data. | AD8: 1. Sign in as Lab Manager. 2. Refresh notifications after report release. 3. Save or submit. 4. Refresh or reopen the record. 5. Compare the result with the pass condition. | AE8: Authorised users receive the correct report-release notification where implemented. | AF8: Notification not received when report released | AG8: Output/reporting issue: generated document, barcode, print, or download behavior needs correction. | AH8: Fix Notifications workflow for "Check report release notification" so actual behavior matches expected result: Authorised users receive the correct report-release notification where implemented. | AJ8: Defect SS
A9: BUG-008 | B9: DL2047 | C9: L1-019 | D9: Level 1 | E9: Doctor Portal | G9: View the referred patient's report | H9: Smoke | I9: Doctor Regular | J9: High | K9: Yes | L9: Failed | M9: Functional Bug | N9: High | O9: Open | P9: Unassigned | R9: 46268 | U9: Not Required | V9: Open | W9: =IF(R9="","",TODAY()-R9) -> 15 | X9: UAT | AB9: Required master data and user exist. | AC9: Use dedicated non-production test data. | AD9: 1. Sign in as Doctor Regular. 2. Sign in as the linked doctor and open the referred patient. 3. Save or submit. 4. Refresh or reopen the record. 5. Compare the result with the pass condition. | AE9: Only owned referrals and Released reports are visible. | AF9: The doctor was created successfully with the commission percentage given, but that is not reflected in the Doctor details UI. Also, when I tried to log in as a doctor, the message showed that access was denied. So, I have tried to provide access for a doctor, but I am unable to save the changes. Also, please remove doctor roles from the Roles and Permissions area. | AG9: Access/RBAC setup issue: required role or permission does not allow the testcase workflow to complete. | AH9: Fix Doctor Portal workflow for "View the referred patient's report" so actual behavior matches expected result: Only owned referrals and Released reports are visible. | AK9: Need to fix the bug
A10: BUG-009 | B10: DL2050 | C10: L1-022 | D10: Level 1 | E10: Billing | G10: Complete payment | H10: Smoke | I10: Billing Cashier | J10: Critical | K10: Yes | L10: Failed | M10: Functional Bug | N10: Medium | O10: Open | P10: Unassigned | U10: Not Required | V10: Open | W10: =IF(R10="","",TODAY()-R10) | X10: UAT | AA10: Stephen | AB10: Required master data and user exist. | AC10: Use dedicated non-production test data. | AD10: 1. Sign in as Billing Cashier. 2. Pay the remaining balance and issue the final receipt. 3. Save or submit. 4. Refresh or reopen the record. 5. Compare the result with the pass condition. | AE10: Bill status becomes Paid and balance becomes zero. | AF10: The total bill amount has been paid. But the pending amount is still showing in the view bill. | AG10: Billing/accounts workflow issue: financial transaction or document flow needs developer rework. | AH10: Fix Billing workflow for "Complete payment" so actual behavior matches expected result: Bill status becomes Paid and balance becomes zero.
A11: BUG-010 | B11: DL2158 | C11: L2-006 | D11: Level 2 | E11: Authentication & Session | G11: Reset token reuse | H11: Security | I11: Tenant User | J11: High | K11: No | L11: Failed | M11: Functional Bug | N11: High | O11: Open | P11: Unassigned | R11: 46269 | U11: Not Required | V11: Open | W11: =IF(R11="","",TODAY()-R11) -> 14 | X11: QA | AA11: Rishidharshini | AB11: Required master data and user exist. | AC11: Use dedicated non-production test data. | AD11: 1. Sign in as Tenant User. 2. Use a reset credential twice. 3. Save or submit. 4. Refresh or reopen the record. 5. Compare the result with the pass condition. | AE11: The second use is denied. | AF11: The second use is not denied. The current password and the new password are the same. | AG11: Failed result requires rework: The second use is not denied. The current password and the new password are the same. | AH11: Fix Authentication & Session workflow for "Reset token reuse" so actual behavior matches expected result: The second use is denied. | AJ11: Defect SS
A12: BUG-011 | B12: DL2161 | C12: L2-009 | D12: Level 2 | E12: Authentication & Session | G12: Session expiry | H12: Functional | I12: Tenant User | J12: Medium | K12: No | L12: Failed | M12: Functional Bug | N12: Medium | O12: Open | P12: Unassigned | R12: 46269 | U12: Not Required | V12: Open | W12: =IF(R12="","",TODAY()-R12) -> 14 | X12: QA | AA12: Rishidharshini | AB12: Required master data and user exist. | AC12: Use dedicated non-production test data. | AD12: 1. Sign in as Tenant User. 2. Use an expired session on UI and API. 3. Save or submit. 4. Refresh or reopen the record. 5. Compare the result with the pass condition. | AE12: The user is asked to sign in again. | AF12: The user is not asked to sign in again. | AG12: Inventory workflow issue: stock, UOM, expiry, or master data behavior does not meet expected result. | AH12: Fix Authentication & Session workflow for "Session expiry" so actual behavior matches expected result: The user is asked to sign in again. | AJ12: Defect SS
A13: BUG-012 | B13: DL2013 | C13: L2-013 | D13: Level 2 | E13: RBAC & Settings | G13: Dangerous permission grant | H13: Functional | J13: Critical | K13: Yes | L13: N/A | M13: N/A Scope Review | N13: Low | O13: Needs Review | P13: Varshini | Q13: 18/09/2026 | R13: 46269 | U13: Pending | V13: Scope Review Pending | W13: =IF(R13="","",TODAY()-R13) -> 14 | X13: UAT | AA13: Abinesh | AB13: Required master data and user exist. | AC13: Use dedicated non-production test data. | AD13: 1. Sign in as Admin. 2. Grant refund, release or user-management permission. 3. Save or submit. 4. Refresh or reopen the record. 5. Compare the result with the pass condition. | AE13: The grant follows the approved control and is auditable. | AG13: N/A case requires QA/Product confirmation: mark as valid non-applicable, deferred scope, or convert to executable test. | AH13: Review with QA/Product, document N/A justification, and update testcase status or scope decision.
A14: BUG-013 | B14: DL2166 | C14: L2-014 | D14: Level 2 | E14: RBAC & Settings | G14: Assigned role deletion | H14: Functional | I14: Admin | J14: Medium | K14: No | L14: Failed | M14: Functional Bug | N14: High | O14: Open | P14: Unassigned | R14: 46268 | U14: Not Required | V14: Open | W14: =IF(R14="","",TODAY()-R14) -> 15 | X14: UAT | AA14: Abinesh | AB14: Required master data and user exist. | AC14: Use dedicated non-production test data. | AD14: 1. Sign in as Admin. 2. Try to delete a role assigned to a user. 3. Save or submit. 4. Refresh or reopen the record. 5. Compare the result with the pass condition. | AE14: Deletion is blocked. | AF14: The Lab Manager role was deleted even though it was already assigned to another user. After deletion, the system automatically assigned the first available role to the affected user. The user can then access the system based on the permissions of the newly assigned role. | AG14: Access/RBAC setup issue: required role or permission does not allow the testcase workflow to complete. | AH14: Fix RBAC & Settings workflow for "Assigned role deletion" so actual behavior matches expected result: Deletion is blocked. | AJ14: Defect SS
A15: BUG-014 | B15: DL2017 | C15: L2-017 | D15: Level 2 | E15: RBAC & Settings | G15: Disabled module API | H15: Functional | I15: Admin | J15: Medium | K15: No | L15: N/A | M15: N/A Scope Review | N15: Low | O15: Needs Review | P15: Kavin | Q15: 18/09/2026 | R15: 46268 | U15: Pending | V15: Scope Review Pending | W15: =IF(R15="","",TODAY()-R15) -> 15 | X15: UAT | AA15: Abinesh | AB15: Required master data and user exist. | AC15: Use dedicated non-production test data. | AD15: 1. Sign in as Admin. 2. Call the disabled module API directly. 3. Save or submit. 4. Refresh or reopen the record. 5. Compare the result with the pass condition. | AE15: The server denies the action. | AG15: N/A case requires QA/Product confirmation: mark as valid non-applicable, deferred scope, or convert to executable test. | AH15: Review with QA/Product, document N/A justification, and update testcase status or scope decision.
A16: BUG-015 | B16: DL2018 | C16: L2-018 | D16: Level 2 | E16: RBAC & Settings | G16: Technician collection denial | H16: Functional | I16: Admin | J16: Medium | K16: No | L16: Failed | M16: Functional Bug | N16: Medium | O16: Open | P16: Unassigned | R16: 46268 | U16: Not Required | V16: Open | W16: =IF(R16="","",TODAY()-R16) -> 15 | X16: UAT | AA16: Abinesh | AB16: Required master data and user exist. | AC16: Use dedicated non-production test data. | AD16: 1. Sign in as Admin. 2. Use Lab Technician to collect a sample. 3. Save or submit. 4. Refresh or reopen the record. 5. Compare the result with the pass condition. | AE16: The default role is denied. | AF16: The system should display a confirmation message when the Collect Sample permission is assigned to the Lab Technician role. | AG16: Access/RBAC setup issue: required role or permission does not allow the testcase workflow to complete. | AH16: Fix RBAC & Settings workflow for "Technician collection denial" so actual behavior matches expected result: The default role is denied. | AJ16: Defect SS
A17: BUG-016 | B17: DL2019 | C17: L2-019 | D17: Level 2 | E17: RBAC & Settings | G17: Technician release denial | H17: Functional | I17: Admin | J17: Medium | K17: No | L17: Failed | M17: Functional Bug | N17: Medium | O17: Open | P17: Unassigned | R17: 46268 | U17: Not Required | V17: Open | W17: =IF(R17="","",TODAY()-R17) -> 15 | X17: UAT | AA17: Abinesh | AB17: Required master data and user exist. | AC17: Use dedicated non-production test data. | AD17: 1. Sign in as Admin. 2. Use Lab Technician to release a report. 3. Save or submit. 4. Refresh or reopen the record. 5. Compare the result with the pass condition. | AE17: The default role is denied. | AF17: The system should display a confirmation message when the release a report permission is assigned to the Lab Technician role. | AG17: Access/RBAC setup issue: required role or permission does not allow the testcase workflow to complete. | AH17: Fix RBAC & Settings workflow for "Technician release denial" so actual behavior matches expected result: The default role is denied. | AJ17: Defect SS
A18: BUG-017 | B18: DL2021 | C18: L2-021 | D18: Level 2 | E18: RBAC & Settings | G18: Role change audit | H18: Functional | I18: Admin | J18: High | K18: No | L18: Failed | M18: Functional Bug | N18: High | O18: Open | P18: Unassigned | R18: 46268 | U18: Not Required | V18: Open | W18: =IF(R18="","",TODAY()-R18) -> 15 | X18: UAT | AA18: Abinesh | AB18: Required master data and user exist. | AC18: User : Abinesh Role : Account Manager Access Removed: Test, Inventory , Users | AD18: 1. Sign in as Admin. 2. Create and update a role. 3. Save or submit. 4. Refresh or reopen the record. 5. Compare the result with the pass condition. | AE18: Actor, old/new permissions and time are auditable. | AF18: Some permissions were removed from the Account Manager role, but the permission changes were not recorded in the Audit Log. The transaction details are missing from the audit records. | AG18: Access/RBAC setup issue: required role or permission does not allow the testcase workflow to complete. | AH18: Fix RBAC & Settings workflow for "Role change audit" so actual behavior matches expected result: Actor, old/new permissions and time are auditable. | AJ18: Defect SS
A19: BUG-018 | B19: DL2021 | C19: L2-022 | D19: Level 2 | E19: RBAC & Settings | G19: Inactive role | H19: Functional | I19: Admin | J19: Medium | K19: No | L19: Failed | M19: Functional Bug | N19: Medium | O19: Open | P19: Unassigned | R19: 46268 | U19: Not Required | V19: Open | W19: =IF(R19="","",TODAY()-R19) -> 15 | X19: UAT | AA19: Abinesh | AB19: Required master data and user exist. | AC19: Use dedicated non-production test data. | AD19: 1. Sign in as Admin. 2. Deactivate a role and try to use it. 3. Save or submit. 4. Refresh or reopen the record. 5. Compare the result with the pass condition. | AE19: The role cannot grant access. | AF19: The Active/Deactivate option is not available in the Role Assignment module, so the role assignment cannot be deactivated. | AG19: Access/RBAC setup issue: required role or permission does not allow the testcase workflow to complete. | AH19: Fix RBAC & Settings workflow for "Inactive role" so actual behavior matches expected result: The role cannot grant access. | AJ19: Defect SS | AK19: The Active/Deactivate option is missing from the Role Assignment module. As a result, the Admin cannot deactivate a user's role assignment as required by the test scenario.
A20: BUG-019 | B20: DL2029 | C20: L2-029 | D20: Level 2 | E20: Patients & Visits | G20: Edit patient | H20: Functional | I20: Front Desk Receptionist | J20: Medium | K20: No | L20: Failed | M20: Functional Bug | N20: Medium | O20: Open | P20: Unassigned | U20: Not Required | V20: Open | W20: =IF(R20="","",TODAY()-R20) | X20: UAT | AA20: Stephen | AB20: Required master data and user exist. | AC20: Use dedicated non-production test data. | AD20: 1. Sign in as Front Desk Receptionist. 2. Change allowed demographics and refresh. 3. Save or submit. 4. Refresh or reopen the record. 5. Compare the result with the pass condition. | AE20: Changes persist and linked records remain intact. | AF20: The patient information details have been changed, but cant working update profile option. | AG20: Failed result requires rework: The patient information details have been changed, but cant working update profile option. | AH20: Fix Patients & Visits workflow for "Edit patient" so actual behavior matches expected result: Changes persist and linked records remain intact.
A21: BUG-020 | B21: DL2032 | C21: L2-032 | D21: Level 2 | E21: Patients & Visits | G21: Soft delete and restore | H21: Functional | I21: Front Desk Receptionist | J21: Medium | K21: No | L21: Failed | M21: Functional Bug | N21: Medium | O21: Open | P21: Unassigned | U21: Not Required | V21: Open | W21: =IF(R21="","",TODAY()-R21) | X21: UAT | AA21: Stephen | AB21: Required master data and user exist. | AC21: Use dedicated non-production test data. | AD21: 1. Sign in as Front Desk Receptionist. 2. Delete and restore a patient. 3. Save or submit. 4. Refresh or reopen the record. 5. Compare the result with the pass condition. | AE21: History and links are preserved. | AF21: There are no patient restore options. | AG21: Failed result requires rework: There are no patient restore options. | AH21: Fix Patients & Visits workflow for "Soft delete and restore" so actual behavior matches expected result: History and links are preserved.
A22: BUG-021 | B22: DL2033 | C22: L2-033 | D22: Level 2 | E22: Patients & Visits | G22: Patient edit audit | H22: Functional | I22: Front Desk Receptionist | J22: Medium | K22: No | L22: Failed | M22: Functional Bug | N22: Medium | O22: Open | P22: Unassigned | U22: Not Required | V22: Open | W22: =IF(R22="","",TODAY()-R22) | X22: UAT | AA22: Stephen | AB22: Required master data and user exist. | AC22: Use dedicated non-production test data. | AD22: 1. Sign in as Front Desk Receptionist. 2. Change identity-sensitive fields. 3. Save or submit. 4. Refresh or reopen the record. 5. Compare the result with the pass condition. | AE22: Old/new values, actor and time are auditable. | AF22: The patient information details have been changed, but cant working update profile option. | AG22: Failed result requires rework: The patient information details have been changed, but cant working update profile option. | AH22: Fix Patients & Visits workflow for "Patient edit audit" so actual behavior matches expected result: Old/new values, actor and time are auditable.
A23: BUG-022 | B23: DL2036 | C23: L2-036 | D23: Level 2 | E23: Doctors & Commission | G23: Duplicate email | H23: Functional | I23: Admin | J23: Medium | K23: No | L23: Failed | M23: Functional Bug | N23: High | O23: Open | P23: Unassigned | R23: 46268 | U23: Not Required | V23: Open | W23: =IF(R23="","",TODAY()-R23) -> 15 | X23: UAT | AA23: Abinesh | AB23: Required master data and user exist. | AC23: Use dedicated non-production test data. | AD23: 1. Sign in as Admin. 2. Create two doctors with the same email. 3. Save or submit. 4. Refresh or reopen the record. 5. Compare the result with the pass condition. | AE23: Duplicate doctor/portal identity is blocked. | AF23: The system allows two doctors to be created with the same email address. No duplicate email validation message is displayed, and the second doctor record is saved successfully. | AG23: Validation/UI rule issue: field constraints or required-field behavior do not match expected workflow. | AH23: Fix Doctors & Commission workflow for "Duplicate email" so actual behavior matches expected result: Duplicate doctor/portal identity is blocked. | AJ23: Defect SS
A24: BUG-023 | B24: DL2039 | C24: L2-039 | D24: Level 2 | E24: Doctors & Commission | G24: Resend invitation | H24: Functional | I24: Admin | J24: Medium | K24: No | L24: Failed | M24: Functional Bug | N24: Medium | O24: Open | P24: Unassigned | R24: 46268 | U24: Not Required | V24: Open | W24: =IF(R24="","",TODAY()-R24) -> 15 | X24: UAT | AA24: Abinesh | AB24: Required master data and user exist. | AC24: Use dedicated non-production test data. | AD24: 1. Sign in as Admin. 2. Resend and try old and new OTPs. 3. Save or submit. 4. Refresh or reopen the record. 5. Compare the result with the pass condition. | AE24: Only the latest OTP works. | AF24: After the doctor successfully submits the OTP and logs in, resending the invitation OTP displays the message “This portal already has an active account.” | AG24: Portal/authentication workflow issue: login, activation, access, or visibility needs correction. | AH24: Fix Doctors & Commission workflow for "Resend invitation" so actual behavior matches expected result: Only the latest OTP works. | AJ24: Defect SS
A25: BUG-024 | B25: DL2040 | C25: L2-040 | D25: Level 2 | E25: Doctors & Commission | G25: Inactive doctor billing | H25: Functional | I25: Admin | J25: Medium | K25: No | L25: Failed | M25: Functional Bug | N25: Low | O25: Open | P25: Unassigned | R25: 46268 | U25: Not Required | V25: Open | W25: =IF(R25="","",TODAY()-R25) -> 15 | X25: UAT | AA25: Abinesh | AB25: Required master data and user exist. | AC25: Use dedicated non-production test data. | AD25: 1. Sign in as Admin. 2. Select an inactive referral doctor. 3. Save or submit. 4. Refresh or reopen the record. 5. Compare the result with the pass condition. | AE25: New billing is blocked. | AF25: When registering a patient, the inactive doctor does not appear in the Referral Code (LOV). When an existing patient is updated from “Doctor Referral = No” to “Yes”, the selected referral doctor is not updated in the patient record. | AG25: Billing/accounts workflow issue: financial transaction or document flow needs developer rework. | AH25: Fix Doctors & Commission workflow for "Inactive doctor billing" so actual behavior matches expected result: New billing is blocked. | AJ25: Defect SS | AK25: This scenario has already been tested by Stephen under test case DL-20029, and the appropriate screenshot has been added to the document as evidence.
A26: BUG-025 | B26: DL2043 | C26: L2-043 | D26: Level 2 | E26: Doctors & Commission | G26: Commission eligibility | H26: Functional | I26: Admin | J26: Medium | K26: No | L26: N/A | M26: N/A Scope Review | N26: Low | O26: Needs Review | P26: Unassigned | R26: 46268 | U26: Not Required | V26: Scope Review Pending | W26: =IF(R26="","",TODAY()-R26) -> 15 | X26: UAT | AA26: Abinesh | AB26: Required master data and user exist. | AC26: Use dedicated non-production test data. | AD26: 1. Sign in as Admin. 2. Compare unpaid, partial and paid referrals. 3. Save or submit. 4. Refresh or reopen the record. 5. Compare the result with the pass condition. | AE26: Estimated and earned commission follow policy. | AG26: N/A case requires QA/Product confirmation: mark as valid non-applicable, deferred scope, or convert to executable test. | AH26: Review with QA/Product, document N/A justification, and update testcase status or scope decision.
A27: BUG-026 | B27: DL2044 | C27: L2-044 | D27: Level 2 | E27: Doctors & Commission | G27: Payout approval | H27: Functional | I27: Admin | J27: High | K27: No | L27: Failed | M27: Functional Bug | N27: High | O27: Open | P27: Unassigned | R27: 46268 | U27: Not Required | V27: Open | W27: =IF(R27="","",TODAY()-R27) -> 15 | X27: UAT | AA27: Abinesh | AB27: Required master data and user exist. | AC27: Use dedicated non-production test data. | AD27: 1. Sign in as Admin. 2. Create and release a payout. 3. Save or submit. 4. Refresh or reopen the record. 5. Compare the result with the pass condition. | AE27: Only authorized staff can approve and the action is auditable. | AF27: The payout was released successfully, but there was no approval by an authorized user, and the payout transaction was not recorded in the Audit Log. | AG27: Failed result requires rework: The payout was released successfully, but there was no approval by an authorized user, and the payout transaction was not recorded in the Audit Log. | AH27: Fix Doctors & Commission workflow for "Payout approval" so actual behavior matches expected result: Only authorized staff can approve and the action is auditable. | AJ27: Defect SS
A28: BUG-027 | B28: DL2046 | C28: L2-046 | D28: Level 2 | E28: Doctors & Commission | G28: Doctor delete protection | H28: Functional | I28: Admin | J28: Medium | K28: No | L28: Failed | M28: Functional Bug | N28: Medium | O28: Open | P28: Unassigned | R28: 46268 | U28: Not Required | V28: Open | W28: =IF(R28="","",TODAY()-R28) -> 15 | X28: UAT | AA28: Abinesh | AB28: Required master data and user exist. | AC28: Use dedicated non-production test data. | AD28: 1. Sign in as Admin. 2. Try to delete a doctor with referrals. 3. Save or submit. 4. Refresh or reopen the record. 5. Compare the result with the pass condition. | AE28: Deletion is blocked or safely archived. | AF28: The system allows the doctor to be deleted even though the doctor has existing referral records.The deletion action is also not recorded in the Audit Log. | AG28: Failed result requires rework: The system allows the doctor to be deleted even though the doctor has existing referral records.The deletion action is also not recorded in the Audit Log. | AH28: Fix Doctors & Commission workflow for "Doctor delete protection" so actual behavior matches expected result: Deletion is blocked or safely archived. | AJ28: Defect SS
A29: BUG-028 | B29: DL2052 | C29: L2-052 | D29: Level 2 | E29: Test Master | G29: Package invalid member | H29: Functional | I29: Lab Manager | J29: Medium | K29: No | L29: Failed | M29: Functional Bug | N29: Medium | O29: Open | P29: Unassigned | R29: 46268 | U29: Not Required | V29: Open | W29: =IF(R29="","",TODAY()-R29) -> 15 | X29: QA | AA29: Rishidharshini | AB29: Required master data and user exist. | AC29: Use dedicated non-production test data. | AD29: 1. Sign in as Lab Manager. 2. Add inactive/duplicate tests to a package. 3. Save or submit. 4. Refresh or reopen the record. 5. Compare the result with the pass condition. | AE29: Invalid package setup is blocked. | AF29: Able to add an inactive test to the package | AG29: Failed result requires rework: Able to add an inactive test to the package | AH29: Fix Test Master workflow for "Package invalid member" so actual behavior matches expected result: Invalid package setup is blocked. | AJ29: Defect SS
A30: BUG-029 | B30: DL2054 | C30: L2-054 | D30: Level 2 | E30: Test Master | G30: Deactivate test | H30: Functional | I30: Lab Manager | J30: Medium | K30: No | L30: Failed | M30: Functional Bug | N30: Medium | O30: Open | P30: Unassigned | R30: 46268 | U30: Not Required | V30: Open | W30: =IF(R30="","",TODAY()-R30) -> 15 | X30: QA | AA30: Rishidharshini | AB30: Required master data and user exist. | AC30: Use dedicated non-production test data. | AD30: 1. Sign in as Lab Manager. 2. Deactivate a test after old bills exist. 3. Save or submit. 4. Refresh or reopen the record. 5. Compare the result with the pass condition. | AE30: Old snapshots remain; new billing cannot select it. | AF30: It is coming in the New billing even it is inactive | AG30: Billing/accounts workflow issue: financial transaction or document flow needs developer rework. | AH30: Fix Test Master workflow for "Deactivate test" so actual behavior matches expected result: Old snapshots remain; new billing cannot select it. | AJ30: Defect SS
A31: BUG-030 | B31: DL2056 | C31: L2-056 | D31: Level 2 | E31: Test Master | G31: Age-specific ranges | H31: Functional | I31: Lab Manager | J31: Medium | K31: No | L31: Failed | M31: Functional Bug | N31: Medium | O31: Open | P31: Unassigned | R31: 46268 | U31: Not Required | V31: Open | W31: =IF(R31="","",TODAY()-R31) -> 15 | X31: QA | AA31: Rishidharshini | AB31: Required master data and user exist. | AC31: Use dedicated non-production test data. | AD31: 1. Sign in as Lab Manager. 2. Configure/test age-dependent references. 3. Save or submit. 4. Refresh or reopen the record. 5. Compare the result with the pass condition. | AE31: Results use the correct range or the gap is recorded. | AF31: There is no test age | AG31: Failed result requires rework: There is no test age | AH31: Fix Test Master workflow for "Age-specific ranges" so actual behavior matches expected result: Results use the correct range or the gap is recorded. | AJ31: Defect SS
A32: BUG-031 | B32: DL2062 | C32: L2-062 | D32: Level 2 | E32: Billing & Payments | G32: Discount limit | H32: Functional | I32: Billing Cashier | J32: Medium | K32: No | L32: Failed | M32: Functional Bug | N32: Medium | O32: Open | P32: Unassigned | U32: Not Required | V32: Open | W32: =IF(R32="","",TODAY()-R32) | X32: UAT | AA32: Stephen | AB32: Required master data and user exist. | AC32: Use dedicated non-production test data. | AD32: 1. Sign in as Billing Cashier. 2. Apply an excessive or unauthorized discount. 3. Save or submit. 4. Refresh or reopen the record. 5. Compare the result with the pass condition. | AE32: Action is blocked and audited. | AF32: The discount amount is not restricted. | AG32: Billing/accounts workflow issue: financial transaction or document flow needs developer rework. | AH32: Fix Billing & Payments workflow for "Discount limit" so actual behavior matches expected result: Action is blocked and audited.
A33: BUG-032 | B33: DL2067 | C33: L2-067 | D33: Level 2 | E33: Billing & Payments | G33: Multiple modes | H33: Functional | I33: Billing Cashier | J33: Medium | K33: No | L33: Failed | M33: Functional Bug | N33: Medium | O33: Open | P33: Unassigned | U33: Not Required | V33: Open | W33: =IF(R33="","",TODAY()-R33) | X33: UAT | AA33: Stephen | AB33: Required master data and user exist. | AC33: Use dedicated non-production test data. | AD33: 1. Sign in as Billing Cashier. 2. Pay using cash, card, UPI, cheque and corporate credit. 3. Save or submit. 4. Refresh or reopen the record. 5. Compare the result with the pass condition. | AE33: Mode breakdown and history are correct. | AF33: Payment details can't work. | AG33: Billing/accounts workflow issue: financial transaction or document flow needs developer rework. | AH33: Fix Billing & Payments workflow for "Multiple modes" so actual behavior matches expected result: Mode breakdown and history are correct.
A34: BUG-033 | B34: DL2070 | C34: L2-070 | D34: Level 2 | E34: Billing & Payments | G34: Cancellation reason | H34: Functional | I34: Billing Cashier | J34: Medium | K34: No | L34: Failed | M34: Functional Bug | N34: Medium | O34: Open | P34: Unassigned | U34: Not Required | V34: Open | W34: =IF(R34="","",TODAY()-R34) | X34: UAT | AA34: Stephen | AB34: Required master data and user exist. | AC34: Use dedicated non-production test data. | AD34: 1. Sign in as Billing Cashier. 2. Cancel a bill without and with a reason. 3. Save or submit. 4. Refresh or reopen the record. 5. Compare the result with the pass condition. | AE34: Reason is required and downstream behavior follows policy. | AF34: The cancel reason field can't be shown. | AG34: Validation/UI rule issue: field constraints or required-field behavior do not match expected workflow. | AH34: Fix Billing & Payments workflow for "Cancellation reason" so actual behavior matches expected result: Reason is required and downstream behavior follows policy.
A35: BUG-034 | B35: DL2071 | C35: L2-071 | D35: Level 2 | E35: Billing & Payments | G35: Refund | H35: Functional | I35: Billing Cashier | J35: Critical | K35: Yes | L35: Failed | M35: Functional Bug | N35: Medium | O35: Open | P35: Unassigned | U35: Not Required | V35: Open | W35: =IF(R35="","",TODAY()-R35) | X35: UAT | AA35: Stephen | AB35: Required master data and user exist. | AC35: Use dedicated non-production test data. | AD35: 1. Sign in as Billing Cashier. 2. Refund a paid/cancelled bill. 3. Save or submit. 4. Refresh or reopen the record. 5. Compare the result with the pass condition. | AE35: Authorized refund reverses amounts and records history. | AF35: The revert reason has options. But the revert reason is important. So please ensure the revert reason is required. | AG35: Validation/UI rule issue: field constraints or required-field behavior do not match expected workflow. | AH35: Fix Billing & Payments workflow for "Refund" so actual behavior matches expected result: Authorized refund reverses amounts and records history.
A36: BUG-035 | B36: DL2073 | C36: L2-073 | D36: Level 2 | E36: Billing & Payments | G36: Corporate credit | H36: Functional | I36: Billing Cashier | J36: Medium | K36: No | L36: Failed | M36: Functional Bug | N36: Medium | O36: Open | P36: Unassigned | U36: Not Required | V36: Open | W36: =IF(R36="","",TODAY()-R36) | X36: UAT | AA36: Stephen | AB36: Required master data and user exist. | AC36: Use dedicated non-production test data. | AD36: 1. Sign in as Billing Cashier. 2. Bill an active corporate account. 3. Save or submit. 4. Refresh or reopen the record. 5. Compare the result with the pass condition. | AE36: Receivable and statement are correct. | AF36: Unable to settle bill using corporate credit. | AG36: Billing/accounts workflow issue: financial transaction or document flow needs developer rework. | AH36: Fix Billing & Payments workflow for "Corporate credit" so actual behavior matches expected result: Receivable and statement are correct.
A37: BUG-036 | B37: DL2074 | C37: L2-074 | D37: Level 2 | E37: Billing & Payments | G37: Credit limit | H37: Functional | I37: Billing Cashier | J37: Medium | K37: No | L37: Failed | M37: Functional Bug | N37: Medium | O37: Open | P37: Unassigned | U37: Not Required | V37: Open | W37: =IF(R37="","",TODAY()-R37) | X37: UAT | AA37: Stephen | AB37: Required master data and user exist. | AC37: Use dedicated non-production test data. | AD37: 1. Sign in as Billing Cashier. 2. Exceed corporate credit limit. 3. Save or submit. 4. Refresh or reopen the record. 5. Compare the result with the pass condition. | AE37: Warning/block follows policy. | AF37: Unable to settle bill using corporate credit. | AG37: Billing/accounts workflow issue: financial transaction or document flow needs developer rework. | AH37: Fix Billing & Payments workflow for "Credit limit" so actual behavior matches expected result: Warning/block follows policy.
A38: BUG-037 | B38: DL2077 | C38: L2-077 | D38: Level 2 | E38: Samples | G38: Automatic sample creation | H38: Functional | I38: Phlebotomist | J38: Medium | K38: No | L38: Failed | M38: Functional Bug | N38: Medium | O38: Open | P38: Unassigned | U38: Not Required | V38: Open | W38: =IF(R38="","",TODAY()-R38) | X38: QA | AA38: Stephen | AB38: Required master data and user exist. | AC38: Use dedicated non-production test data. | AD38: 1. Sign in as Phlebotomist. 2. Create a multi-test bill. 3. Save or submit. 4. Refresh or reopen the record. 5. Compare the result with the pass condition. | AE38: Correct samples/investigations are linked. | AF38: Can't create an appropriate role. | AG38: Access/RBAC setup issue: required role or permission does not allow the testcase workflow to complete. | AH38: Fix Samples workflow for "Automatic sample creation" so actual behavior matches expected result: Correct samples/investigations are linked.
A39: BUG-038 | B39: DL2078 | C39: L2-078 | D39: Level 2 | E39: Samples | G39: Unique sample ID | H39: Functional | I39: Phlebotomist | J39: Medium | K39: No | L39: Failed | M39: Functional Bug | N39: Medium | O39: Open | P39: Unassigned | U39: Not Required | V39: Open | W39: =IF(R39="","",TODAY()-R39) | X39: QA | AA39: Stephen | AB39: Required master data and user exist. | AC39: Use dedicated non-production test data. | AD39: 1. Sign in as Phlebotomist. 2. Create many samples concurrently. 3. Save or submit. 4. Refresh or reopen the record. 5. Compare the result with the pass condition. | AE39: Every sample ID and barcode is unique. | AF39: Can't create an appropriate role. | AG39: Access/RBAC setup issue: required role or permission does not allow the testcase workflow to complete. | AH39: Fix Samples workflow for "Unique sample ID" so actual behavior matches expected result: Every sample ID and barcode is unique.
A40: BUG-039 | B40: DL2079 | C40: L2-079 | D40: Level 2 | E40: Samples | G40: Collection time validation | H40: Functional | I40: Phlebotomist | J40: Medium | K40: No | L40: Failed | M40: Functional Bug | N40: Medium | O40: Open | P40: Unassigned | U40: Not Required | V40: Open | W40: =IF(R40="","",TODAY()-R40) | X40: QA | AA40: Stephen | AB40: Required master data and user exist. | AC40: Use dedicated non-production test data. | AD40: 1. Sign in as Phlebotomist. 2. Enter future or pre-DOB collection time. 3. Save or submit. 4. Refresh or reopen the record. 5. Compare the result with the pass condition. | AE40: Invalid time is blocked. | AF40: Can't create an appropriate role. | AG40: Access/RBAC setup issue: required role or permission does not allow the testcase workflow to complete. | AH40: Fix Samples workflow for "Collection time validation" so actual behavior matches expected result: Invalid time is blocked.
A41: BUG-040 | B41: DL2080 | C41: L2-080 | D41: Level 2 | E41: Samples | G41: Received time order | H41: Functional | I41: Phlebotomist | J41: Medium | K41: No | L41: Failed | M41: Functional Bug | N41: Medium | O41: Open | P41: Unassigned | U41: Not Required | V41: Open | W41: =IF(R41="","",TODAY()-R41) | X41: QA | AA41: Stephen | AB41: Required master data and user exist. | AC41: Use dedicated non-production test data. | AD41: 1. Sign in as Phlebotomist. 2. Enter received time before collection. 3. Save or submit. 4. Refresh or reopen the record. 5. Compare the result with the pass condition. | AE41: Invalid order is blocked. | AF41: Can't create an appropriate role. | AG41: Access/RBAC setup issue: required role or permission does not allow the testcase workflow to complete. | AH41: Fix Samples workflow for "Received time order" so actual behavior matches expected result: Invalid order is blocked.
A42: BUG-041 | B42: DL2081 | C42: L2-081 | D42: Level 2 | E42: Samples | G42: Valid status sequence | H42: Functional | I42: Phlebotomist | J42: Medium | K42: No | L42: Failed | M42: Functional Bug | N42: Medium | O42: Open | P42: Unassigned | U42: Not Required | V42: Open | W42: =IF(R42="","",TODAY()-R42) | X42: QA | AA42: Stephen | AB42: Required master data and user exist. | AC42: Use dedicated non-production test data. | AD42: 1. Sign in as Phlebotomist. 2. Move Registered to Collected to Processing to Completed. 3. Save or submit. 4. Refresh or reopen the record. 5. Compare the result with the pass condition. | AE42: Each transition persists with custody history. | AF42: Can't create an appropriate role. | AG42: Access/RBAC setup issue: required role or permission does not allow the testcase workflow to complete. | AH42: Fix Samples workflow for "Valid status sequence" so actual behavior matches expected result: Each transition persists with custody history.
A43: BUG-042 | B43: DL2082 | C43: L2-082 | D43: Level 2 | E43: Samples | G43: Invalid status jump | H43: Functional | I43: Phlebotomist | J43: Medium | K43: No | L43: Failed | M43: Functional Bug | N43: Medium | O43: Open | P43: Unassigned | U43: Not Required | V43: Open | W43: =IF(R43="","",TODAY()-R43) | X43: QA | AA43: Stephen | AB43: Required master data and user exist. | AC43: Use dedicated non-production test data. | AD43: 1. Sign in as Phlebotomist. 2. Jump Registered directly to Completed/Released. 3. Save or submit. 4. Refresh or reopen the record. 5. Compare the result with the pass condition. | AE43: Transition is blocked. | AF43: Can't create an appropriate role. | AG43: Access/RBAC setup issue: required role or permission does not allow the testcase workflow to complete. | AH43: Fix Samples workflow for "Invalid status jump" so actual behavior matches expected result: Transition is blocked.
... A53: BUG-052 | B53: DL2092 | C53: L2-092 | D53: Level 2 | E53: Samples | G53: Sample audit | H53: Functional | I53: Phlebotomist | J53: Medium | K53: No | L53: Failed | M53: Functional Bug | N53: Medium | O53: Open | P53: Unassigned | U53: Not Required | V53: Open | W53: =IF(R53="","",TODAY()-R53) | X53: QA | AA53: Stephen | AB53: Required master data and user exist. | AC53: Use dedicated non-production test data. | AD53: 1. Sign in as Phlebotomist. 2. Collect, reject and complete samples. 3. Save or submit. 4. Refresh or reopen the record. 5. Compare the result with the pass condition. | AE53: All sensitive sample changes are auditable. | AF53: Can't create an appropriate role. | AG53: Access/RBAC setup issue: required role or permission does not allow the testcase workflow to complete. | AH53: Fix Samples workflow for "Sample audit" so actual behavior matches expected result: All sensitive sample changes are auditable.
A54: BUG-053 | B54: DL2093 | C54: L2-093 | D54: Level 2 | E54: Reports | G54: Required result | H54: Functional | I54: Pathologist | J54: Medium | K54: No | L54: Failed | M54: Functional Bug | N54: Medium | O54: Open | P54: Unassigned | R54: 46268 | U54: Not Required | V54: Open | W54: =IF(R54="","",TODAY()-R54) -> 15 | X54: QA | AA54: Rishidharshini | AB54: Required master data and user exist. | AC54: Use dedicated non-production test data. | AD54: 1. Sign in as Pathologist. 2. Leave a required result empty. 3. Save or submit. 4. Refresh or reopen the record. 5. Compare the result with the pass condition. | AE54: Review is blocked. | AF54: This is in the sample module, not the report module | AG54: Validation/UI rule issue: field constraints or required-field behavior do not match expected workflow. | AH54: Fix Reports workflow for "Required result" so actual behavior matches expected result: Review is blocked. | AJ54: Defect SS
A55: BUG-054 | B55: DL2094 | C55: L2-094 | D55: Level 2 | E55: Reports | G55: Invalid numeric result | H55: Functional | I55: Pathologist | J55: Medium | K55: No | L55: Failed | M55: Functional Bug | N55: Medium | O55: Open | P55: Unassigned | R55: 46268 | U55: Not Required | V55: Open | W55: =IF(R55="","",TODAY()-R55) -> 15 | X55: QA | AA55: Rishidharshini | AB55: Required master data and user exist. | AC55: Use dedicated non-production test data. | AD55: 1. Sign in as Pathologist. 2. Enter text or exponential notation in a numeric field. 3. Save or submit. 4. Refresh or reopen the record. 5. Compare the result with the pass condition. | AE55: Invalid input is blocked. | AF55: This is in the sample module, not the report module. Even in the sample module, invalid input is not blocked when entering it; it takes normal input. | AG55: Output/reporting issue: generated document, barcode, print, or download behavior needs correction. | AH55: Fix Reports workflow for "Invalid numeric result" so actual behavior matches expected result: Invalid input is blocked. | AJ55: Defect SS
A56: BUG-055 | B56: DL2096 | C56: L2-096 | D56: Level 2 | E56: Reports | G56: Draft edit | H56: Functional | I56: Pathologist | J56: Medium | K56: No | L56: Failed | M56: Functional Bug | N56: Medium | O56: Open | P56: Unassigned | R56: 46268 | U56: Not Required | V56: Open | W56: =IF(R56="","",TODAY()-R56) -> 15 | X56: QA | AA56: Rishidharshini | AB56: Required master data and user exist. | AC56: Use dedicated non-production test data. | AD56: 1. Sign in as Pathologist. 2. Edit a Draft report. 3. Save or submit. 4. Refresh or reopen the record. 5. Compare the result with the pass condition. | AE56: Changes save and version behavior is correct. | AF56: Cannot edit the draft report. Only the draft report can be deleted | AG56: Output/reporting issue: generated document, barcode, print, or download behavior needs correction. | AH56: Fix Reports workflow for "Draft edit" so actual behavior matches expected result: Changes save and version behavior is correct. | AJ56: Defect SS
A57: BUG-056 | B57: DL2097 | C57: L2-097 | D57: Level 2 | E57: Reports | G57: Reviewed edit | H57: Functional | I57: Pathologist | J57: Medium | K57: No | L57: Failed | M57: Functional Bug | N57: Medium | O57: Open | P57: Unassigned | R57: 46268 | U57: Not Required | V57: Open | W57: =IF(R57="","",TODAY()-R57) -> 15 | X57: QA | AA57: Rishidharshini | AB57: Required master data and user exist. | AC57: Use dedicated non-production test data. | AD57: 1. Sign in as Pathologist. 2. Try to edit a Reviewed report as a typist. 3. Save or submit. 4. Refresh or reopen the record. 5. Compare the result with the pass condition. | AE57: Unauthorized/status-invalid edit is blocked. | AF57: A pathologist cannot release a report as a typist | AG57: Output/reporting issue: generated document, barcode, print, or download behavior needs correction. | AH57: Fix Reports workflow for "Reviewed edit" so actual behavior matches expected result: Unauthorized/status-invalid edit is blocked. | AJ57: Defect SS
A58: BUG-057 | B58: DL2100 | C58: L2-100 | D58: Level 2 | E58: Reports | G58: Wrong role release | H58: Functional | I58: Pathologist | J58: Medium | K58: No | L58: Failed | M58: Functional Bug | N58: Medium | O58: Open | P58: Unassigned | R58: 46268 | U58: Not Required | V58: Open | W58: =IF(R58="","",TODAY()-R58) -> 15 | X58: QA | AA58: Rishidharshini | AB58: Required master data and user exist. | AC58: Use dedicated non-production test data. | AD58: 1. Sign in as Pathologist. 2. Release as Technician or Front Desk without permission. 3. Save or submit. 4. Refresh or reopen the record. 5. Compare the result with the pass condition. | AE58: Server and UI deny release. | AF58: A pathologist cannot release a report as a technician or front desk | AG58: Access/RBAC setup issue: required role or permission does not allow the testcase workflow to complete. | AH58: Fix Reports workflow for "Wrong role release" so actual behavior matches expected result: Server and UI deny release. | AJ58: Defect SS
A59: BUG-058 | B59: DL2106 | C59: L2-106 | D59: Level 2 | E59: Reports | G59: Post-release correction | H59: Functional | I59: Pathologist | J59: Critical | K59: Yes | L59: Failed | M59: Functional Bug | N59: High | O59: Open | P59: Unassigned | R59: 46268 | U59: Not Required | V59: Open | W59: =IF(R59="","",TODAY()-R59) -> 15 | X59: QA | AA59: Rishidharshini | AB59: Required master data and user exist. | AC59: Use dedicated non-production test data. | AD59: 1. Sign in as Pathologist. 2. Correct a Released report with a reason and approval. 3. Save or submit. 4. Refresh or reopen the record. 5. Compare the result with the pass condition. | AE59: Original remains; amendment is approved and portals show correct version. | AF59: Once released, the report cannot be amended | AG59: Output/reporting issue: generated document, barcode, print, or download behavior needs correction. | AH59: Fix Reports workflow for "Post-release correction" so actual behavior matches expected result: Original remains; amendment is approved and portals show correct version. | AJ59: Defect SS
A60: BUG-059 | B60: DL2108 | C60: L2-108 | D60: Level 2 | E60: Reports | G60: Release audit | H60: Functional | I60: Pathologist | J60: Critical | K60: Yes | L60: Failed | M60: Functional Bug | N60: High | O60: Open | P60: Unassigned | R60: 46268 | U60: Not Required | V60: Open | W60: =IF(R60="","",TODAY()-R60) -> 15 | X60: QA | AA60: Rishidharshini | AB60: Required master data and user exist. | AC60: Use dedicated non-production test data. | AD60: 1. Sign in as Pathologist. 2. Review, approve, release and amend. 3. Save or submit. 4. Refresh or reopen the record. 5. Compare the result with the pass condition. | AE60: Actor, time, status and version are auditable. | AF60: Once released, the report cannot be amended | AG60: Output/reporting issue: generated document, barcode, print, or download behavior needs correction. | AH60: Fix Reports workflow for "Release audit" so actual behavior matches expected result: Actor, time, status and version are auditable. | AJ60: Defect SS
A61: BUG-060 | B61: DL2112 | C61: L2-112 | D61: Level 2 | E61: Inventory | G61: Batch receipt | H61: Functional | I61: Inventory Manager | J61: Medium | K61: No | L61: Failed | M61: Functional Bug | N61: High | O61: Open | P61: Unassigned | R61: 46268 | U61: Pending | V61: Open | W61: =IF(R61="","",TODAY()-R61) -> 15 | X61: UAT | AA61: Premothan V | AB61: Required master data and user exist. | AC61: Use dedicated non-production test data. | AD61: 1. Sign in as Inventory Manager. 2. Receive two batches with different expiry dates. 3. Save or submit. 4. Refresh or reopen the record. 5. Compare the result with the pass condition. | AE61: Both batches and totals are correct. | AF61: If I tried to create a new batch with the same item code, it generated an error like same item code. But here, only the batch will change. No item code will have to change. | AG61: Billing/accounts workflow issue: financial transaction or document flow needs developer rework. | AH61: Fix Inventory workflow for "Batch receipt" so actual behavior matches expected result: Both batches and totals are correct. | AK61: Need to retest
A62: BUG-061 | B62: DL2114 | C62: L2-114 | D62: Level 2 | E62: Inventory | G62: Negative stock | H62: Functional | I62: Inventory Manager | J62: Medium | K62: No | L62: Failed | M62: Functional Bug | N62: High | O62: Open | P62: Unassigned | R62: 46268 | U62: Pending | V62: Open | W62: =IF(R62="","",TODAY()-R62) -> 15 | X62: UAT | AA62: Premothan V | AB62: Required master data and user exist. | AC62: Use dedicated non-production test data. | AD62: 1. Sign in as Inventory Manager. 2. Issue more than available. 3. Save or submit. 4. Refresh or reopen the record. 5. Compare the result with the pass condition. | AE62: Negative stock is blocked or controlled by approved override. | AF62: I tried to purchase more stock than the provided limit. It actually accepted. But this is one that must not be extended | AG62: Inventory workflow issue: stock, UOM, expiry, or master data behavior does not meet expected result. | AH62: Fix Inventory workflow for "Negative stock" so actual behavior matches expected result: Negative stock is blocked or controlled by approved override. | AK62: Need to retest
A63: BUG-062 | B63: DL2115 | C63: L2-115 | D63: Level 2 | E63: Inventory | G63: Low stock | H63: Functional | I63: Inventory Manager | J63: Medium | K63: No | L63: Failed | M63: Functional Bug | N63: High | O63: Open | P63: Unassigned | R63: 46268 | U63: Pending | V63: Open | W63: =IF(R63="","",TODAY()-R63) -> 15 | X63: UAT | AA63: Premothan V | AB63: Required master data and user exist. | AC63: Use dedicated non-production test data. | AD63: 1. Sign in as Inventory Manager. 2. Move stock below reorder level. 3. Save or submit. 4. Refresh or reopen the record. 5. Compare the result with the pass condition. | AE63: Low-stock warning/notification appears. | AF63: Here, reorder the stock level, but unable to edit items, error popup | AG63: Inventory workflow issue: stock, UOM, expiry, or master data behavior does not meet expected result. | AH63: Fix Inventory workflow for "Low stock" so actual behavior matches expected result: Low-stock warning/notification appears. | AK63: Need to retest
A64: BUG-063 | B64: DL2116 | C64: L2-116 | D64: Level 2 | E64: Inventory | G64: Expired stock | H64: Functional | I64: Inventory Manager | J64: Medium | K64: No | L64: Failed | M64: Functional Bug | N64: Low | O64: Open | P64: Unassigned | R64: 46269 | U64: Pending | V64: Open | W64: =IF(R64="","",TODAY()-R64) -> 14 | X64: UAT | AA64: Premothan V | AB64: Required master data and user exist. | AC64: Use dedicated non-production test data. | AD64: 1. Sign in as Inventory Manager. 2. Try to reserve/use an expired batch. 3. Save or submit. 4. Refresh or reopen the record. 5. Compare the result with the pass condition. | AE64: Expired stock is blocked. | AF64: Unable to set the expired date as current and for previous dates. This has to be changed | AG64: Inventory workflow issue: stock, UOM, expiry, or master data behavior does not meet expected result. | AH64: Fix Inventory workflow for "Expired stock" so actual behavior matches expected result: Expired stock is blocked. | AK64: Need to retest
A65: BUG-064 | B65: DL2118 | C65: L2-118 | D65: Level 2 | E65: Inventory | G65: Automatic consumption | H65: Functional | I65: Inventory Manager | J65: Critical | K65: Yes | L65: N/A | M65: N/A Scope Review | N65: Low | O65: Needs Review | P65: Unassigned | U65: Not Required | V65: Scope Review Pending | W65: =IF(R65="","",TODAY()-R65) | X65: QA | AB65: Required master data and user exist. | AC65: Use dedicated non-production test data. | AD65: 1. Sign in as Inventory Manager. 2. Complete a test linked to inventory. 3. Save or submit. 4. Refresh or reopen the record. 5. Compare the result with the pass condition. | AE65: Configured quantity is consumed once or the gap blocks release. | AF65: Not available for this Inventory Manager | AG65: N/A scope decision required: Not available for this Inventory Manager | AH65: Review with QA/Product, document N/A justification, and update testcase status or scope decision.
A66: BUG-065 | B66: DL2119 | C66: L2-119 | D66: Level 2 | E66: Inventory | G66: Insufficient stock | H66: Functional | I66: Inventory Manager | J66: Medium | K66: No | L66: N/A | M66: N/A Scope Review | N66: Low | O66: Needs Review | P66: Unassigned | U66: Not Required | V66: Scope Review Pending | W66: =IF(R66="","",TODAY()-R66) | X66: QA | AB66: Required master data and user exist. | AC66: Use dedicated non-production test data. | AD66: 1. Sign in as Inventory Manager. 2. Start a test with insufficient required stock. 3. Save or submit. 4. Refresh or reopen the record. 5. Compare the result with the pass condition. | AE66: Warning/block follows the approved policy. | AF66: Not available for Inventory Manager | AG66: N/A scope decision required: Not available for Inventory Manager | AH66: Review with QA/Product, document N/A justification, and update testcase status or scope decision.
A67: BUG-066 | B67: DL2120 | C67: L2-120 | D67: Level 2 | E67: Inventory | G67: Reservation release | H67: Functional | I67: Inventory Manager | J67: Medium | K67: No | L67: N/A | M67: N/A Scope Review | N67: Low | O67: Needs Review | P67: Unassigned | U67: Not Required | V67: Scope Review Pending | W67: =IF(R67="","",TODAY()-R67) | X67: QA | AB67: Required master data and user exist. | AC67: Use dedicated non-production test data. | AD67: 1. Sign in as Inventory Manager. 2. Reject/cancel a sample after reservation. 3. Save or submit. 4. Refresh or reopen the record. 5. Compare the result with the pass condition. | AE67: Reserved stock is released correctly. | AF67: Not available for this Inventory Manager | AG67: N/A scope decision required: Not available for this Inventory Manager | AH67: Review with QA/Product, document N/A justification, and update testcase status or scope decision.
A68: BUG-067 | B68: DL2122 | C68: L2-122 | D68: Level 2 | E68: Inventory | G68: Purchase approval | H68: Functional | I68: Inventory Manager | J68: Medium | K68: No | L68: N/A | M68: N/A Scope Review | N68: Low | O68: Needs Review | P68: Unassigned | U68: Not Required | V68: Scope Review Pending | W68: =IF(R68="","",TODAY()-R68) | X68: QA | AB68: Required master data and user exist. | AC68: Use dedicated non-production test data. | AD68: 1. Sign in as Inventory Manager. 2. Approve/reject a purchase order. 3. Save or submit. 4. Refresh or reopen the record. 5. Compare the result with the pass condition. | AE68: Only authorized users can approve. | AF68: Not available for this version | AG68: N/A scope decision required: Not available for this version | AH68: Review with QA/Product, document N/A justification, and update testcase status or scope decision.
A69: BUG-068 | B69: DL2123 | C69: L2-123 | D69: Level 2 | E69: Inventory | G69: Import/export | H69: Functional | I69: Inventory Manager | J69: Medium | K69: No | L69: Failed | M69: Functional Bug | N69: Medium | O69: Open | P69: Unassigned | R69: 46268 | U69: Not Required | V69: Open | W69: =IF(R69="","",TODAY()-R69) -> 15 | X69: UAT | AA69: Premothan V | AB69: Required master data and user exist. | AC69: Use dedicated non-production test data. | AD69: 1. Sign in as Inventory Manager. 2. Import valid/invalid inventory and export the result. 3. Save or submit. 4. Refresh or reopen the record. 5. Compare the result with the pass condition. | AE69: Valid rows load, errors are clear and export reconciles. | AF69: There is no option here to export the result | AG69: Inventory workflow issue: stock, UOM, expiry, or master data behavior does not meet expected result. | AH69: Fix Inventory workflow for "Import/export" so actual behavior matches expected result: Valid rows load, errors are clear and export reconciles. | AK69: Have to retest
A70: BUG-069 | B70: DL2125 | C70: L2-125 | D70: Level 2 | E70: Accounts, Corporate & Expenses | G70: Invoice journal | H70: Functional | I70: Accounts Manager | J70: Medium | K70: No | L70: Failed | M70: Functional Bug | N70: Medium | O70: Open | P70: Unassigned | R70: 46269 | U70: Not Required | V70: Open | W70: =IF(R70="","",TODAY()-R70) -> 14 | X70: UAT | AA70: Abinesh | AB70: Required master data and user exist. | AC70: Use dedicated non-production test data. | AD70: 1. Sign in as Accounts Manager. 2. Create a bill. 3. Save or submit. 4. Refresh or reopen the record. 5. Compare the result with the pass condition. | AE70: Receivable/revenue journal is balanced and linked. | AF70: The bill was created successfully and closed with an amount of ₹7,200. However, the ₹7,200 is not reflected in the “Revenue” section of the Accounts Dashboard. The same amount is correctly reflected in the “Total Collection” section of the Reports Dashboard. | AG70: Output/reporting issue: generated document, barcode, print, or download behavior needs correction. | AH70: Fix Accounts, Corporate & Expenses workflow for "Invoice journal" so actual behavior matches expected result: Receivable/revenue journal is balanced and linked. | AJ70: Defect SS | AK70: The closed bill amount is reflected in Total Collection but is not updated in Revenue on the Accounts Dashboard
A71: BUG-070 | B71: DL2127 | C71: L2-127 | D71: Level 2 | E71: Accounts, Corporate & Expenses | G71: Refund journal | H71: Functional | I71: Accounts Manager | J71: Medium | K71: No | L71: Failed | M71: Functional Bug | N71: Medium | O71: Open | P71: Unassigned | R71: 46269 | U71: Not Required | V71: Open | W71: =IF(R71="","",TODAY()-R71) -> 14 | X71: UAT | AA71: Abinesh | AB71: Required master data and user exist. | AC71: Use dedicated non-production test data. | AD71: 1. Sign in as Accounts Manager. 2. Refund a payment. 3. Save or submit. 4. Refresh or reopen the record. 5. Compare the result with the pass condition. | AE71: Reversal is balanced and linked. | AF71: The payment of ₹2,000 was refunded successfully, and the reversal entry was created with the correct amount. The refunded amount is reflected in the “Revenue” section of the Accounts Dashboard but is not reflected in the “Daily Collection” section of the Reports Dashboard. | AG71: Output/reporting issue: generated document, barcode, print, or download behavior needs correction. | AH71: Fix Accounts, Corporate & Expenses workflow for "Refund journal" so actual behavior matches expected result: Reversal is balanced and linked. | AJ71: Defect SS
A72: BUG-071 | B72: DL2128 | C72: L2-128 | D72: Level 2 | E72: Accounts, Corporate & Expenses | G72: Journal balance | H72: Functional | I72: Accounts Manager | J72: Medium | K72: No | L72: Failed | M72: Functional Bug | N72: High | O72: Open | P72: Unassigned | R72: 46269 | U72: Not Required | V72: Open | W72: =IF(R72="","",TODAY()-R72) -> 14 | X72: UAT | AA72: Abinesh | AB72: Required master data and user exist. | AC72: Use dedicated non-production test data. | AD72: 1. Sign in as Accounts Manager. 2. Review generated journals. 3. Save or submit. 4. Refresh or reopen the record. 5. Compare the result with the pass condition. | AE72: Total debit equals total credit. | AF72: When the same account type is selected for both Debit and Credit with equal amounts, the system displays an error message(Unable to post journal entry). However, when different account types are selected for Debit and Credit with equal amounts, the journal entry is submitted successfully. The manual journal entry process is also complicated . | AG72: Failed result requires rework: When the same account type is selected for both Debit and Credit with equal amounts, the system displays an error message(Unable to post journal entry). However, when different account types are selected for Debit and Credit with equal amounts, the journal entry is submitted successfully. The manual journal entry process is also complicated . | AH72: Fix Accounts, Corporate & Expenses workflow for "Journal balance" so actual behavior matches expected result: Total debit equals total credit. | AJ72: Defect SS
A73: BUG-072 | B73: DL2134 | C73: L2-134 | D73: Level 2 | E73: Accounts, Corporate & Expenses | G73: Expense validation | H73: Functional | I73: Accounts Manager | J73: Medium | K73: No | L73: Failed | M73: Functional Bug | N73: Medium | O73: Open | P73: Unassigned | R73: 46269 | U73: Not Required | V73: Open | W73: =IF(R73="","",TODAY()-R73) -> 14 | X73: UAT | AA73: Rishidharshini | AB73: Required master data and user exist. | AC73: Use dedicated non-production test data. | AD73: 1. Sign in as Accounts Manager. 2. Create valid and invalid expenses. 3. Save or submit. 4. Refresh or reopen the record. 5. Compare the result with the pass condition. | AE73: Only valid authorized expense saves. | AF73: Invalid expenses also can submit | AG73: Validation/UI rule issue: field constraints or required-field behavior do not match expected workflow. | AH73: Fix Accounts, Corporate & Expenses workflow for "Expense validation" so actual behavior matches expected result: Only valid authorized expense saves. | AJ73: Defect SS
A74: BUG-073 | B74: DL2135 | C74: L2-135 | D74: Level 2 | E74: Accounts, Corporate & Expenses | G74: Expense approval | H74: Functional | I74: Accounts Manager | J74: Medium | K74: No | L74: N/A | M74: N/A Scope Review | N74: Low | O74: Needs Review | P74: Unassigned | R74: 46269 | U74: Not Required | V74: Scope Review Pending | W74: =IF(R74="","",TODAY()-R74) -> 14 | X74: UAT | AA74: Rishidharshini | AB74: Required master data and user exist. | AC74: Use dedicated non-production test data. | AD74: 1. Sign in as Accounts Manager. 2. Submit and approve/reject an expense. 3. Save or submit. 4. Refresh or reopen the record. 5. Compare the result with the pass condition. | AE74: Approval history is complete. | AF74: This option is not in the application | AG74: N/A scope decision required: This option is not in the application | AH74: Review with QA/Product, document N/A justification, and update testcase status or scope decision.
A75: BUG-074 | B75: DL2137 | C75: L2-137 | D75: Level 2 | E75: Accounts, Corporate & Expenses | G75: Recurring expense | H75: Functional | I75: Accounts Manager | J75: Medium | K75: No | L75: Failed | M75: Functional Bug | N75: Medium | O75: Open | P75: Unassigned | R75: 46269 | U75: Not Required | V75: Open | W75: =IF(R75="","",TODAY()-R75) -> 14 | X75: UAT | AA75: Rishidharshini | AB75: Required master data and user exist. | AC75: Use dedicated non-production test data. | AD75: 1. Sign in as Accounts Manager. 2. Create and generate a recurring expense. 3. Save or submit. 4. Refresh or reopen the record. 5. Compare the result with the pass condition. | AE75: No missed or duplicate entries. | AF75: Duplicate entries are coming in the expenses | AG75: Failed result requires rework: Duplicate entries are coming in the expenses | AH75: Fix Accounts, Corporate & Expenses workflow for "Recurring expense" so actual behavior matches expected result: No missed or duplicate entries. | AJ75: Defect SS
A76: BUG-075 | B76: DL2138 | C76: L2-138 | D76: Level 2 | E76: Accounts, Corporate & Expenses | G76: Corporate statement | H76: Functional | I76: Accounts Manager | J76: Medium | K76: No | L76: Failed | M76: Functional Bug | N76: Medium | O76: Open | P76: Unassigned | R76: 46269 | U76: Not Required | V76: Open | W76: =IF(R76="","",TODAY()-R76) -> 14 | X76: UAT | AA76: Rishidharshini | AB76: Required master data and user exist. | AC76: Use dedicated non-production test data. | AD76: 1. Sign in as Accounts Manager. 2. Generate a statement for a date range. 3. Save or submit. 4. Refresh or reopen the record. 5. Compare the result with the pass condition. | AE76: Opening, bills, payments and closing balance reconcile. | AF76: Date filters are not available for Billing and payment | AG76: Billing/accounts workflow issue: financial transaction or document flow needs developer rework. | AH76: Fix Accounts, Corporate & Expenses workflow for "Corporate statement" so actual behavior matches expected result: Opening, bills, payments and closing balance reconcile. | AJ76: Defect SS
A77: BUG-076 | B77: DL2139 | C77: L2-139 | D77: Level 2 | E77: Accounts, Corporate & Expenses | G77: Corporate aging | H77: Functional | I77: Accounts Manager | J77: Medium | K77: No | L77: N/A | M77: N/A Scope Review | N77: Low | O77: Needs Review | P77: Unassigned | R77: 46269 | U77: Not Required | V77: Scope Review Pending | W77: =IF(R77="","",TODAY()-R77) -> 14 | X77: UAT | AA77: Rishidharshini | AB77: Required master data and user exist. | AC77: Use dedicated non-production test data. | AD77: 1. Sign in as Accounts Manager. 2. Age outstanding corporate invoices. 3. Save or submit. 4. Refresh or reopen the record. 5. Compare the result with the pass condition. | AE77: Aging buckets are correct. | AF77: Invoices are not available | AG77: N/A scope decision required: Invoices are not available | AH77: Review with QA/Product, document N/A justification, and update testcase status or scope decision.
A78: BUG-077 | B78: DL2140 | C78: L2-140 | D78: Level 2 | E78: Accounts, Corporate & Expenses | G78: Daily close/reopen | H78: Functional | I78: Accounts Manager | J78: Medium | K78: No | L78: N/A | M78: N/A Scope Review | N78: Low | O78: Needs Review | P78: Unassigned | R78: 46269 | U78: Not Required | V78: Scope Review Pending | W78: =IF(R78="","",TODAY()-R78) -> 14 | X78: UAT | AA78: Rishidharshini | AB78: Required master data and user exist. | AC78: Use dedicated non-production test data. | AD78: 1. Sign in as Accounts Manager. 2. Close, attempt late entry and authorized reopen. 3. Save or submit. 4. Refresh or reopen the record. 5. Compare the result with the pass condition. | AE78: Policy, reason and audit are enforced. | AF78: Not available | AG78: N/A scope decision required: Not available | AH78: Review with QA/Product, document N/A justification, and update testcase status or scope decision.
A79: BUG-078 | B79: DL2141 | C79: L2-141 | D79: Level 2 | E79: Accounts, Corporate & Expenses | G79: Financial export | H79: Functional | I79: Accounts Manager | J79: Medium | K79: No | L79: Failed | M79: Functional Bug | N79: Medium | O79: Open | P79: Unassigned | R79: 46269 | U79: Not Required | V79: Open | W79: =IF(R79="","",TODAY()-R79) -> 14 | X79: UAT | AA79: Rishidharshini | AB79: Required master data and user exist. | AC79: Use dedicated non-production test data. | AD79: 1. Sign in as Accounts Manager. 2. Export ledger, P&L and statements. 3. Save or submit. 4. Refresh or reopen the record. 5. Compare the result with the pass condition. | AE79: Export matches screen totals. | AF79: PDF export cannot be done; others are working, like Excel and CSV. | AG79: Output/reporting issue: generated document, barcode, print, or download behavior needs correction. | AH79: Fix Accounts, Corporate & Expenses workflow for "Financial export" so actual behavior matches expected result: Export matches screen totals. | AJ79: Defect SS
A80: BUG-079 | B80: DL2152 | C80: L2-152 | D80: Level 2 | E80: Doctor & Patient Portals | G80: Reissue patient slip | H80: Functional | I80: Portal User | J80: Medium | K80: No | L80: Failed | M80: Functional Bug | N80: Medium | O80: Open | P80: Unassigned | U80: Not Required | V80: Open | W80: =IF(R80="","",TODAY()-R80) | X80: QA | AA80: Stephen | AB80: Required master data and user exist. | AC80: Use dedicated non-production test data. | AD80: 1. Sign in as Portal User. 2. Issue a new slip after active login. 3. Save or submit. 4. Refresh or reopen the record. 5. Compare the result with the pass condition. | AE80: Old credentials and sessions are invalidated. | AF80: This field is not available | AG80: Validation/UI rule issue: field constraints or required-field behavior do not match expected workflow. | AH80: Fix Doctor & Patient Portals workflow for "Reissue patient slip" so actual behavior matches expected result: Old credentials and sessions are invalidated.
A81: BUG-080 | B81: DL2155 | C81: L2-155 | D81: Level 2 | E81: Doctor & Patient Portals | G81: Portal print | H81: Functional | I81: Portal User | J81: Medium | K81: No | L81: Failed | M81: Functional Bug | N81: High | O81: Open | P81: Unassigned | R81: 46269 | U81: Pending | V81: Open | W81: =IF(R81="","",TODAY()-R81) -> 14 | X81: UAT | AA81: Premothan V | AB81: Required master data and user exist. | AC81: Use dedicated non-production test data. | AD81: 1. Sign in as Portal User. 2. Print a Released report from patient and doctor portals. 3. Save or submit. 4. Refresh or reopen the record. 5. Compare the result with the pass condition. | AE81: Correct report prints without hidden internal data. | AF81: Unable to print a report. Also, for the doctor, we do not have a released report list | AG81: Output/reporting issue: generated document, barcode, print, or download behavior needs correction. | AH81: Fix Doctor & Patient Portals workflow for "Portal print" so actual behavior matches expected result: Correct report prints without hidden internal data. | AK81: Have to retest after fix
A82: BUG-081 | B82: DL2156 | C82: L2-156 | D82: Level 2 | E82: Doctor & Patient Portals | G82: Portal audit | H82: Functional | I82: Portal User | J82: Medium | K82: No | L82: Failed | M82: Functional Bug | N82: High | O82: Open | P82: Unassigned | R82: 46269 | U82: Pending | V82: Open | W82: =IF(R82="","",TODAY()-R82) -> 14 | X82: UAT | AA82: Premothan V | AB82: Required master data and user exist. | AC82: Use dedicated non-production test data. | AD82: 1. Sign in as Portal User. 2. Login and open a report. 3. Save or submit. 4. Refresh or reopen the record. 5. Compare the result with the pass condition. | AE82: Portal access events are auditable. | AF82: For a non-investor doctor, the patient reports are not generated on his login page. But if the doctor is an investor, he is able to view patient reports | AG82: Output/reporting issue: generated document, barcode, print, or download behavior needs correction. | AH82: Fix Doctor & Patient Portals workflow for "Portal audit" so actual behavior matches expected result: Portal access events are auditable. | AK82: Have to retest after fix
A83: BUG-082 | B83: DL2163 | C83: L2-163 | D83: Level 2 | E83: Dashboard, Search, Notifications & Analytics | G83: Read/unread state | H83: Functional | I83: Lab Manager | J83: Medium | K83: No | L83: Failed | M83: Functional Bug | N83: Medium | O83: Open | P83: Unassigned | R83: 46268 | U83: Not Required | V83: Open | W83: =IF(R83="","",TODAY()-R83) -> 15 | X83: QA | AA83: Rishidharshini | AB83: Required master data and user exist. | AC83: Use dedicated non-production test data. | AD83: 1. Sign in as Lab Manager. 2. Mark notification read and reload. 3. Save or submit. 4. Refresh or reopen the record. 5. Compare the result with the pass condition. | AE83: State persists. | AF83: Notifications are not shown | AG83: Failed result requires rework: Notifications are not shown | AH83: Fix Dashboard, Search, Notifications & Analytics workflow for "Read/unread state" so actual behavior matches expected result: State persists. | AJ83: Defect SS
A84: BUG-083 | B84: DL2164 | C84: L2-164 | D84: Level 2 | E84: Dashboard, Search, Notifications & Analytics | G84: Notification preferences | H84: Functional | I84: Lab Manager | J84: Medium | K84: No | L84: Failed | M84: Functional Bug | N84: Medium | O84: Open | P84: Unassigned | R84: 46268 | U84: Not Required | V84: Open | W84: =IF(R84="","",TODAY()-R84) -> 15 | X84: QA | AA84: Rishidharshini | AB84: Required master data and user exist. | AC84: Use dedicated non-production test data. | AD84: 1. Sign in as Lab Manager. 2. Disable a notification category. 3. Save or submit. 4. Refresh or reopen the record. 5. Compare the result with the pass condition. | AE84: Preference is respected. | AF84: There is no Notification category | AG84: Failed result requires rework: There is no Notification category | AH84: Fix Dashboard, Search, Notifications & Analytics workflow for "Notification preferences" so actual behavior matches expected result: Preference is respected. | AJ84: Defect SS
A85: BUG-084 | B85: DL2171 | C85: L2-171 | D85: Level 2 | E85: Developer, Subscription & Tenant | G85: Module plan | H85: Functional | I85: Developer Admin | J85: Medium | K85: No | L85: Failed | M85: Functional Bug | N85: High | O85: Open | P85: Unassigned | R85: 46266 | U85: Pending | V85: Open | W85: =IF(R85="","",TODAY()-R85) -> 17 | X85: UAT | AA85: Premothan V | AB85: Required master data and user exist. | AC85: Use dedicated non-production test data. | AD85: 1. Sign in as Developer Admin. 2. Change subscription plan/modules. 3. Save or submit. 4. Refresh or reopen the record. 5. Compare the result with the pass condition. | AE85: Navigation and APIs follow the new plan. | AF85: I changed it to a standard subscription again after the 6th staff was created. But still, it maintained the 6th staff. Therefore, the lab admin needs to ensure one staff removal. Because if this is accepted like this. This will lead to misuse. | AG85: Failed result requires rework: I changed it to a standard subscription again after the 6th staff was created. But still, it maintained the 6th staff. Therefore, the lab admin needs to ensure one staff removal. Because if this is accepted like this. This will lead to misuse. | AH85: Fix Developer, Subscription & Tenant workflow for "Module plan" so actual behavior matches expected result: Navigation and APIs follow the new plan.
A86: BUG-085 | B86: DL2173 | C86: L2-173 | D86: Level 2 | E86: Developer, Subscription & Tenant | G86: Upgrade request | H86: Functional | I86: Developer Admin | J86: Medium | K86: No | L86: Failed | M86: Functional Bug | N86: High | O86: Open | P86: Unassigned | R86: 46267 | U86: Pending | V86: Open | W86: =IF(R86="","",TODAY()-R86) -> 16 | X86: UAT | AA86: Premothan V | AB86: Required master data and user exist. | AC86: Use dedicated non-production test data. | AD86: 1. Sign in as Developer Admin. 2. Submit and confirm a subscription upgrade. 3. Save or submit. 4. Refresh or reopen the record. 5. Compare the result with the pass condition. | AE86: Plan changes once with traceable history. | AF86: The same test was done for the previous scenario, and it failed (refer to L2-171), Defect ID: DL2171 | AG86: Failed result requires rework: The same test was done for the previous scenario, and it failed (refer to L2-171), Defect ID: DL2171 | AH86: Fix Developer, Subscription & Tenant workflow for "Upgrade request" so actual behavior matches expected result: Plan changes once with traceable history.

Sheet Developer Rework Summary
A1: Metric | B1: Formula / Value
A2: Total Bugs | B2: =COUNTA('Bug Tracker - 85'!A2:A200) -> 85
A3: Failed Bugs | B3: =COUNTIF('Bug Tracker - 85'!L:L,"Failed") -> 75
A4: N/A Review Bugs | B4: =COUNTIF('Bug Tracker - 85'!L:L,"N/A") -> 10
A5: Open Developer Items | B5: =COUNTIF('Bug Tracker - 85'!O:O,"Open") -> 75
A6: In Progress | B6: =COUNTIF('Bug Tracker - 85'!O:O,"In Progress") -> 0
A7: Fixed | B7: =COUNTIF('Bug Tracker - 85'!O:O,"Fixed") -> 0
A8: Closed | B8: =COUNTIF('Bug Tracker - 85'!V:V,"Closed") -> 0
A9: Unassigned | B9: =COUNTIF('Bug Tracker - 85'!P:P,"Unassigned") -> 83
A10: Critical | B10: =COUNTIF('Bug Tracker - 85'!N:N,"Critical") -> 0
A11: High | B11: =COUNTIF('Bug Tracker - 85'!N:N,"High") -> 20
A12: Medium | B12: =COUNTIF('Bug Tracker - 85'!N:N,"Medium") -> 52
A13: Low | B13: =COUNTIF('Bug Tracker - 85'!N:N,"Low") -> 13
A14: Release Rule | B14: All BUG-001 to BUG-085 must be Closed or formally Deferred before release.

Sheet Module Wise Bugs
A1: Module | B1: Total Bugs | C1: Failed | D1: N/A | E1: Critical | F1: High | G1: Medium | H1: Low | I1: Open/In Progress
A2: Accounts, Corporate & Expenses | B2: =COUNTIF('Bug Tracker - 85'!E:E,A2) -> 10 | C2: =COUNTIFS('Bug Tracker - 85'!E:E,A2,'Bug Tracker - 85'!L:L,"Failed") -> 7 | D2: =COUNTIFS('Bug Tracker - 85'!E:E,A2,'Bug Tracker - 85'!L:L,"N/A") -> 3 | E2: =COUNTIFS('Bug Tracker - 85'!E:E,A2,'Bug Tracker - 85'!N:N,"Critical") -> 0 | F2: =COUNTIFS('Bug Tracker - 85'!E:E,A2,'Bug Tracker - 85'!N:N,"High") -> 1 | G2: =COUNTIFS('Bug Tracker - 85'!E:E,A2,'Bug Tracker - 85'!N:N,"Medium") -> 6 | H2: =COUNTIFS('Bug Tracker - 85'!E:E,A2,'Bug Tracker - 85'!N:N,"Low") -> 3 | I2: =COUNTIFS('Bug Tracker - 85'!E:E,A2,'Bug Tracker - 85'!O:O,"Open")+COUNTIFS('Bug Tracker - 85'!E:E,A2,'Bug Tracker - 85'!O:O,"In Progress") -> 7
A3: Authentication & Session | B3: =COUNTIF('Bug Tracker - 85'!E:E,A3) -> 2 | C3: =COUNTIFS('Bug Tracker - 85'!E:E,A3,'Bug Tracker - 85'!L:L,"Failed") -> 2 | D3: =COUNTIFS('Bug Tracker - 85'!E:E,A3,'Bug Tracker - 85'!L:L,"N/A") -> 0 | E3: =COUNTIFS('Bug Tracker - 85'!E:E,A3,'Bug Tracker - 85'!N:N,"Critical") -> 0 | F3: =COUNTIFS('Bug Tracker - 85'!E:E,A3,'Bug Tracker - 85'!N:N,"High") -> 1 | G3: =COUNTIFS('Bug Tracker - 85'!E:E,A3,'Bug Tracker - 85'!N:N,"Medium") -> 1 | H3: =COUNTIFS('Bug Tracker - 85'!E:E,A3,'Bug Tracker - 85'!N:N,"Low") -> 0 | I3: =COUNTIFS('Bug Tracker - 85'!E:E,A3,'Bug Tracker - 85'!O:O,"Open")+COUNTIFS('Bug Tracker - 85'!E:E,A3,'Bug Tracker - 85'!O:O,"In Progress") -> 2
A4: Billing | B4: =COUNTIF('Bug Tracker - 85'!E:E,A4) -> 1 | C4: =COUNTIFS('Bug Tracker - 85'!E:E,A4,'Bug Tracker - 85'!L:L,"Failed") -> 1 | D4: =COUNTIFS('Bug Tracker - 85'!E:E,A4,'Bug Tracker - 85'!L:L,"N/A") -> 0 | E4: =COUNTIFS('Bug Tracker - 85'!E:E,A4,'Bug Tracker - 85'!N:N,"Critical") -> 0 | F4: =COUNTIFS('Bug Tracker - 85'!E:E,A4,'Bug Tracker - 85'!N:N,"High") -> 0 | G4: =COUNTIFS('Bug Tracker - 85'!E:E,A4,'Bug Tracker - 85'!N:N,"Medium") -> 1 | H4: =COUNTIFS('Bug Tracker - 85'!E:E,A4,'Bug Tracker - 85'!N:N,"Low") -> 0 | I4: =COUNTIFS('Bug Tracker - 85'!E:E,A4,'Bug Tracker - 85'!O:O,"Open")+COUNTIFS('Bug Tracker - 85'!E:E,A4,'Bug Tracker - 85'!O:O,"In Progress") -> 1
A5: Billing & Payments | B5: =COUNTIF('Bug Tracker - 85'!E:E,A5) -> 6 | C5: =COUNTIFS('Bug Tracker - 85'!E:E,A5,'Bug Tracker - 85'!L:L,"Failed") -> 6 | D5: =COUNTIFS('Bug Tracker - 85'!E:E,A5,'Bug Tracker - 85'!L:L,"N/A") -> 0 | E5: =COUNTIFS('Bug Tracker - 85'!E:E,A5,'Bug Tracker - 85'!N:N,"Critical") -> 0 | F5: =COUNTIFS('Bug Tracker - 85'!E:E,A5,'Bug Tracker - 85'!N:N,"High") -> 0 | G5: =COUNTIFS('Bug Tracker - 85'!E:E,A5,'Bug Tracker - 85'!N:N,"Medium") -> 6 | H5: =COUNTIFS('Bug Tracker - 85'!E:E,A5,'Bug Tracker - 85'!N:N,"Low") -> 0 | I5: =COUNTIFS('Bug Tracker - 85'!E:E,A5,'Bug Tracker - 85'!O:O,"Open")+COUNTIFS('Bug Tracker - 85'!E:E,A5,'Bug Tracker - 85'!O:O,"In Progress") -> 6
A6: Dashboard, Search, Notifications & Analytics | B6: =COUNTIF('Bug Tracker - 85'!E:E,A6) -> 2 | C6: =COUNTIFS('Bug Tracker - 85'!E:E,A6,'Bug Tracker - 85'!L:L,"Failed") -> 2 | D6: =COUNTIFS('Bug Tracker - 85'!E:E,A6,'Bug Tracker - 85'!L:L,"N/A") -> 0 | E6: =COUNTIFS('Bug Tracker - 85'!E:E,A6,'Bug Tracker - 85'!N:N,"Critical") -> 0 | F6: =COUNTIFS('Bug Tracker - 85'!E:E,A6,'Bug Tracker - 85'!N:N,"High") -> 0 | G6: =COUNTIFS('Bug Tracker - 85'!E:E,A6,'Bug Tracker - 85'!N:N,"Medium") -> 2 | H6: =COUNTIFS('Bug Tracker - 85'!E:E,A6,'Bug Tracker - 85'!N:N,"Low") -> 0 | I6: =COUNTIFS('Bug Tracker - 85'!E:E,A6,'Bug Tracker - 85'!O:O,"Open")+COUNTIFS('Bug Tracker - 85'!E:E,A6,'Bug Tracker - 85'!O:O,"In Progress") -> 2
A7: Developer, Subscription & Tenant | B7: =COUNTIF('Bug Tracker - 85'!E:E,A7) -> 2 | C7: =COUNTIFS('Bug Tracker - 85'!E:E,A7,'Bug Tracker - 85'!L:L,"Failed") -> 2 | D7: =COUNTIFS('Bug Tracker - 85'!E:E,A7,'Bug Tracker - 85'!L:L,"N/A") -> 0 | E7: =COUNTIFS('Bug Tracker - 85'!E:E,A7,'Bug Tracker - 85'!N:N,"Critical") -> 0 | F7: =COUNTIFS('Bug Tracker - 85'!E:E,A7,'Bug Tracker - 85'!N:N,"High") -> 2 | G7: =COUNTIFS('Bug Tracker - 85'!E:E,A7,'Bug Tracker - 85'!N:N,"Medium") -> 0 | H7: =COUNTIFS('Bug Tracker - 85'!E:E,A7,'Bug Tracker - 85'!N:N,"Low") -> 0 | I7: =COUNTIFS('Bug Tracker - 85'!E:E,A7,'Bug Tracker - 85'!O:O,"Open")+COUNTIFS('Bug Tracker - 85'!E:E,A7,'Bug Tracker - 85'!O:O,"In Progress") -> 2
A8: Doctor & Patient Portals | B8: =COUNTIF('Bug Tracker - 85'!E:E,A8) -> 3 | C8: =COUNTIFS('Bug Tracker - 85'!E:E,A8,'Bug Tracker - 85'!L:L,"Failed") -> 3 | D8: =COUNTIFS('Bug Tracker - 85'!E:E,A8,'Bug Tracker - 85'!L:L,"N/A") -> 0 | E8: =COUNTIFS('Bug Tracker - 85'!E:E,A8,'Bug Tracker - 85'!N:N,"Critical") -> 0 | F8: =COUNTIFS('Bug Tracker - 85'!E:E,A8,'Bug Tracker - 85'!N:N,"High") -> 2 | G8: =COUNTIFS('Bug Tracker - 85'!E:E,A8,'Bug Tracker - 85'!N:N,"Medium") -> 1 | H8: =COUNTIFS('Bug Tracker - 85'!E:E,A8,'Bug Tracker - 85'!N:N,"Low") -> 0 | I8: =COUNTIFS('Bug Tracker - 85'!E:E,A8,'Bug Tracker - 85'!O:O,"Open")+COUNTIFS('Bug Tracker - 85'!E:E,A8,'Bug Tracker - 85'!O:O,"In Progress") -> 3
A9: Doctor Portal | B9: =COUNTIF('Bug Tracker - 85'!E:E,A9) -> 1 | C9: =COUNTIFS('Bug Tracker - 85'!E:E,A9,'Bug Tracker - 85'!L:L,"Failed") -> 1 | D9: =COUNTIFS('Bug Tracker - 85'!E:E,A9,'Bug Tracker - 85'!L:L,"N/A") -> 0 | E9: =COUNTIFS('Bug Tracker - 85'!E:E,A9,'Bug Tracker - 85'!N:N,"Critical") -> 0 | F9: =COUNTIFS('Bug Tracker - 85'!E:E,A9,'Bug Tracker - 85'!N:N,"High") -> 1 | G9: =COUNTIFS('Bug Tracker - 85'!E:E,A9,'Bug Tracker - 85'!N:N,"Medium") -> 0 | H9: =COUNTIFS('Bug Tracker - 85'!E:E,A9,'Bug Tracker - 85'!N:N,"Low") -> 0 | I9: =COUNTIFS('Bug Tracker - 85'!E:E,A9,'Bug Tracker - 85'!O:O,"Open")+COUNTIFS('Bug Tracker - 85'!E:E,A9,'Bug Tracker - 85'!O:O,"In Progress") -> 1
A10: Doctors & Commission | B10: =COUNTIF('Bug Tracker - 85'!E:E,A10) -> 6 | C10: =COUNTIFS('Bug Tracker - 85'!E:E,A10,'Bug Tracker - 85'!L:L,"Failed") -> 5 | D10: =COUNTIFS('Bug Tracker - 85'!E:E,A10,'Bug Tracker - 85'!L:L,"N/A") -> 1 | E10: =COUNTIFS('Bug Tracker - 85'!E:E,A10,'Bug Tracker - 85'!N:N,"Critical") -> 0 | F10: =COUNTIFS('Bug Tracker - 85'!E:E,A10,'Bug Tracker - 85'!N:N,"High") -> 2 | G10: =COUNTIFS('Bug Tracker - 85'!E:E,A10,'Bug Tracker - 85'!N:N,"Medium") -> 2 | H10: =COUNTIFS('Bug Tracker - 85'!E:E,A10,'Bug Tracker - 85'!N:N,"Low") -> 2 | I10: =COUNTIFS('Bug Tracker - 85'!E:E,A10,'Bug Tracker - 85'!O:O,"Open")+COUNTIFS('Bug Tracker - 85'!E:E,A10,'Bug Tracker - 85'!O:O,"In Progress") -> 5
A11: Inventory | B11: =COUNTIF('Bug Tracker - 85'!E:E,A11) -> 11 | C11: =COUNTIFS('Bug Tracker - 85'!E:E,A11,'Bug Tracker - 85'!L:L,"Failed") -> 7 | D11: =COUNTIFS('Bug Tracker - 85'!E:E,A11,'Bug Tracker - 85'!L:L,"N/A") -> 4 | E11: =COUNTIFS('Bug Tracker - 85'!E:E,A11,'Bug Tracker - 85'!N:N,"Critical") -> 0 | F11: =COUNTIFS('Bug Tracker - 85'!E:E,A11,'Bug Tracker - 85'!N:N,"High") -> 4 | G11: =COUNTIFS('Bug Tracker - 85'!E:E,A11,'Bug Tracker - 85'!N:N,"Medium") -> 1 | H11: =COUNTIFS('Bug Tracker - 85'!E:E,A11,'Bug Tracker - 85'!N:N,"Low") -> 6 | I11: =COUNTIFS('Bug Tracker - 85'!E:E,A11,'Bug Tracker - 85'!O:O,"Open")+COUNTIFS('Bug Tracker - 85'!E:E,A11,'Bug Tracker - 85'!O:O,"In Progress") -> 7
A12: Notifications | B12: =COUNTIF('Bug Tracker - 85'!E:E,A12) -> 1 | C12: =COUNTIFS('Bug Tracker - 85'!E:E,A12,'Bug Tracker - 85'!L:L,"Failed") -> 1 | D12: =COUNTIFS('Bug Tracker - 85'!E:E,A12,'Bug Tracker - 85'!L:L,"N/A") -> 0 | E12: =COUNTIFS('Bug Tracker - 85'!E:E,A12,'Bug Tracker - 85'!N:N,"Critical") -> 0 | F12: =COUNTIFS('Bug Tracker - 85'!E:E,A12,'Bug Tracker - 85'!N:N,"High") -> 1 | G12: =COUNTIFS('Bug Tracker - 85'!E:E,A12,'Bug Tracker - 85'!N:N,"Medium") -> 0 | H12: =COUNTIFS('Bug Tracker - 85'!E:E,A12,'Bug Tracker - 85'!N:N,"Low") -> 0 | I12: =COUNTIFS('Bug Tracker - 85'!E:E,A12,'Bug Tracker - 85'!O:O,"Open")+COUNTIFS('Bug Tracker - 85'!E:E,A12,'Bug Tracker - 85'!O:O,"In Progress") -> 1
A13: Patients & Visits | B13: =COUNTIF('Bug Tracker - 85'!E:E,A13) -> 3 | C13: =COUNTIFS('Bug Tracker - 85'!E:E,A13,'Bug Tracker - 85'!L:L,"Failed") -> 3 | D13: =COUNTIFS('Bug Tracker - 85'!E:E,A13,'Bug Tracker - 85'!L:L,"N/A") -> 0 | E13: =COUNTIFS('Bug Tracker - 85'!E:E,A13,'Bug Tracker - 85'!N:N,"Critical") -> 0 | F13: =COUNTIFS('Bug Tracker - 85'!E:E,A13,'Bug Tracker - 85'!N:N,"High") -> 0 | G13: =COUNTIFS('Bug Tracker - 85'!E:E,A13,'Bug Tracker - 85'!N:N,"Medium") -> 3 | H13: =COUNTIFS('Bug Tracker - 85'!E:E,A13,'Bug Tracker - 85'!N:N,"Low") -> 0 | I13: =COUNTIFS('Bug Tracker - 85'!E:E,A13,'Bug Tracker - 85'!O:O,"Open")+COUNTIFS('Bug Tracker - 85'!E:E,A13,'Bug Tracker - 85'!O:O,"In Progress") -> 3
... A18: Test Master | B18: =COUNTIF('Bug Tracker - 85'!E:E,A18) -> 3 | C18: =COUNTIFS('Bug Tracker - 85'!E:E,A18,'Bug Tracker - 85'!L:L,"Failed") -> 3 | D18: =COUNTIFS('Bug Tracker - 85'!E:E,A18,'Bug Tracker - 85'!L:L,"N/A") -> 0 | E18: =COUNTIFS('Bug Tracker - 85'!E:E,A18,'Bug Tracker - 85'!N:N,"Critical") -> 0 | F18: =COUNTIFS('Bug Tracker - 85'!E:E,A18,'Bug Tracker - 85'!N:N,"High") -> 0 | G18: =COUNTIFS('Bug Tracker - 85'!E:E,A18,'Bug Tracker - 85'!N:N,"Medium") -> 3 | H18: =COUNTIFS('Bug Tracker - 85'!E:E,A18,'Bug Tracker - 85'!N:N,"Low") -> 0 | I18: =COUNTIFS('Bug Tracker - 85'!E:E,A18,'Bug Tracker - 85'!O:O,"Open")+COUNTIFS('Bug Tracker - 85'!E:E,A18,'Bug Tracker - 85'!O:O,"In Progress") -> 3

Sheet Lookup
A1: Developer Bug Rework Maintenance Rule | B1: Details
A2: Step 1 | B2: Assign Developer Name for every Unassigned bug.
A3: Step 2 | B3: Developer fills Developer Rework Date, Reason / Root Cause, Fix Notes, and Fix Build.
A4: Step 3 | B4: QA retests only after Bug Status is Fixed.
A5: Step 4 | B5: Failed retest becomes Reopened; Passed retest becomes Closed.
A6: Step 5 | B6: N/A items need Product/QA approval with written reason before closure/deferment.
A7: Release Gate | B7: No release until all 85 items are Closed or formally Deferred.
A8: Source Workbook | B8: C:\Users\rishi\Downloads\LIMS_Three_Level_Release_Testing_Tracker (1) (2) (1).xlsx
